glue_small_multiples/__init__.py
glue_small_multiples/layer_artist.py
glue_small_multiples/state.py
glue_small_multiples/utils.py
glue_small_multiples/qt/__init__.py
glue_small_multiples/qt/layer_style_editor.py
glue_small_multiples/qt/layer_style_editor.ui
glue_small_multiples/qt/options_widget.py
glue_small_multiples/qt/options_widget.ui
glue_small_multiples/qt/viewer.py
glue_small_multiples/qt/tests/__init__.py
glue_small_multiples/qt/tests/test_axes.py
glue_small_multiples/qt/tests/test_data_viewer.py
glue_small_multiples/qt/tests/test_save_restore.py
glue_small_multiples/qt/tests/data/__init__.py
glue_small_multiples/qt/tests/data/penguins.csv
glue_small_multiples-1.3.dist-info/METADATA
glue_small_multiples-1.3.dist-info/WHEEL
glue_small_multiples-1.3.dist-info/entry_points.txt
glue_small_multiples-1.3.dist-info/top_level.txt
glue_small_multiples-1.3.dist-info/RECORD
