Metadata-Version: 2.2
Name: glue-small-multiples
Version: 1.3
Summary: A viewer for small multiples
Home-page: https://www.gluesolutions.io
Author: glue solutions, inc.
Author-email: jfoster@gluesolutions.io
Classifier: Intended Audience :: Science/Research
Classifier: Operating System :: OS Independent
Classifier: Programming Language :: Python
Classifier: Programming Language :: Python :: 3
Classifier: Programming Language :: Python :: 3.8
Classifier: Programming Language :: Python :: 3.9
Classifier: Programming Language :: Python :: 3.10
Classifier: Programming Language :: Python :: 3.11
Classifier: Topic :: Scientific/Engineering :: Visualization
Classifier: License :: OSI Approved :: BSD License
Requires-Python: >=3.8
Provides-Extra: test
Requires-Dist: pytest; extra == "test"
Requires-Dist: pytest-qt; extra == "test"
Requires-Dist: pytest-faulthandler; extra == "test"
Requires-Dist: mock; extra == "test"
Provides-Extra: qt5
Requires-Dist: PyQt5>=5.9; extra == "qt5"
Provides-Extra: qt6
Requires-Dist: PyQt6; extra == "qt6"
Provides-Extra: glue
Requires-Dist: glue-core; extra == "glue"
Requires-Dist: glue-qt; extra == "glue"
